cdk_7layer_constructs/kinesis_firehose_transformer/__init__.py
cdk_7layer_constructs/kinesis_firehose_transformer/py.typed
cdk_7layer_constructs/kinesis_firehose_transformer/_jsii/__init__.py
cdk_7layer_constructs/kinesis_firehose_transformer/_jsii/kinesis-firehose-transformer@0.1.3.jsii.tgz
cdk_7layer_constructs.kinesis_firehose_transformer-0.1.3.dist-info/METADATA
cdk_7layer_constructs.kinesis_firehose_transformer-0.1.3.dist-info/WHEEL
cdk_7layer_constructs.kinesis_firehose_transformer-0.1.3.dist-info/top_level.txt
cdk_7layer_constructs.kinesis_firehose_transformer-0.1.3.dist-info/RECORD
