Metadata-Version: 2.1
Name: cdk-7layer-constructs.kinesis-firehose-transformer
Version: 0.1.3
Summary: Kinesis Firehose Transformer to automatically convert JSON data sent to Firehose to Parquet
Home-page: https://github.com/randyridgley/cdk-7layer-constructs
Author: Randy Ridgley
License: Apache-2.0
Project-URL: Source, https://github.com/randyridgley/cdk-7layer-constructs.git
Platform: UNKNOWN
Classifier: Intended Audience :: Developers
Classifier: Operating System :: OS Independent
Classifier: Programming Language :: JavaScript
Classifier: Programming Language :: Python :: 3 :: Only
Classifier: Programming Language :: Python :: 3.6
Classifier: Programming Language :: Python :: 3.7
Classifier: Programming Language :: Python :: 3.8
Classifier: Typing :: Typed
Classifier: License :: OSI Approved
Requires-Python: >=3.6
Requires-Dist: jsii (<2.0.0,>=1.9.0)
Requires-Dist: publication (>=0.0.3)
Requires-Dist: aws-cdk.aws-glue (<2.0.0,>=1.56.0)
Requires-Dist: aws-cdk.aws-iam (<2.0.0,>=1.56.0)
Requires-Dist: aws-cdk.aws-kinesisfirehose (<2.0.0,>=1.56.0)
Requires-Dist: aws-cdk.aws-kms (<2.0.0,>=1.56.0)
Requires-Dist: aws-cdk.aws-logs (<2.0.0,>=1.56.0)
Requires-Dist: aws-cdk.aws-s3 (<2.0.0,>=1.56.0)
Requires-Dist: aws-cdk.core (<2.0.0,>=1.56.0)
Requires-Dist: constructs (<4.0.0,>=3.0.4)
